globalMem/__init__.py
globalMem/_version.py
globalMem/auto_init.py
globalMem/global_context.py
globalMem/tools.py
globalmem-0.1.0.dist-info/METADATA
globalmem-0.1.0.dist-info/WHEEL
globalmem-0.1.0.dist-info/entry_points.txt
globalmem-0.1.0.dist-info/top_level.txt
globalmem-0.1.0.dist-info/RECORD
