Metadata-Version: 2.4
Name: globalMem
Version: 0.1.0
Summary: Gestion d'objets globaux accessibles sans import
Author-email: Guillaume Lefebvre <guillaume@ldmail.fr>
Requires-Python: >=3.8
